dynamic_manim_components/__init__.py
dynamic_manim_components/src/animation.py
dynamic_manim_components/src/dynamic_mobject.py
dynamic_manim_components/src/dynamic_tex_mobject.py
dynamic_manim_components/src/numpy_mobject_array.py
dynamic_manim_components/src/manim_src/composition.py
dynamic_manim_components-0.1.9.dist-info/METADATA
dynamic_manim_components-0.1.9.dist-info/WHEEL
dynamic_manim_components-0.1.9.dist-info/top_level.txt
dynamic_manim_components-0.1.9.dist-info/RECORD
