Metadata-Version: 2.1
Name: dynamic-manim-components
Version: 0.1.9
Summary: A ManimCE component library, supporting component composition and automatic animation
Home-page: https://github.com/philip-murray/dynamic-manim-components
Author: Philip Murray
Author-email: philipmurray.code@gmail.com
Requires-Python: >=3.8
Requires-Dist: manim >=0.18.1
